Workbook

Sheet MSBP Consolidated Plan
A1: No | B1: Category | C1: Task / Project | D1: Code | E1: Project Name | F1: Project Lead | G1: Team Collaboration | H1: Progress | I1: Target Date | J1: Start Date | K1: End Date | L1: Status | M1: History Work Accomplishment | N1: Plan Activities (Weekly) | O1: Issue (Risk) | P1: Delay | Q1: User | R1: Folder Link | S1: Lead Email | T1: Collaboration Team Email | U1: Count Project by Name | V1: Column22 | W1: Column21 | X1: Category2 | Y1: NEED 3rd PARTY (Admin) | Z1: PLAN START | AA1: PLAN END | AB1: PLAN DATE | AC1: Effectiv Year
A2: 1 | B2: Management System | C2: ITM Integrated Management System (TIMES) Establishment -Site Level | D2: MS 1.1 | E2: TIMES QMS Deployment - Melak Cluster (Establishment) | F2: ALR | G2: ARS, RRP | H2: 0.85 | I2: 46022 | J2: 45348 | K2: 46022 | L2: Hold | M2: 1. Already conducted Stage 1 (BP Workshop) 2. Already conducted Stage 2 (MS Workshop) 3. Already conducted review and alignment for the BP Design 4. Already coordinate and remind target with DSPM - for operational basis in SOP development 5. Already conducted further discussion regarding Coal Processing process - align with IBU 6. Already conducted socialization agenda to All TCM-BEK related stakeholders regarding BP Level 0 Mapping 7. Already continued the project by giving the TCM & BEK BP to Consultant Team 8. Already ensure and monitor the implementation of MELAK BP Development by Consultant Team | N2: 1. Ensure the socialization of the final deliverables of MELAK BP to all MELAK respective stakeholders 2. Implement the next phase of Governance development | O2: N/A | P2: =Project_Tracker[[#This Row],[End Date]]-Project_Tracker[[#This Row],[Target Date]] -> 0 | S2: =IF(Project_Tracker[[#This Row],[Project Lead]]="", "", IFERROR(VLOOKUP(Project_Tracker[[#This Row],[Project Lead]], Setting!C:D, 2, 0), "")) -> aldy_rienaldy@banpuindo.co.id | U2: =Project_Tracker[[#This Row],[Project Lead]]&", "&Project_Tracker[[#This Row],[Team Collaboration]] -> ALR, ARS, RRP | AC2: 2025
A3: 2 | B3: Management System | C3: ITM Integrated Management System (TIMES) Establishment -Site Level | D3: MS 1.2 | E3: TIMES QMS Deployment - JBG (Establishment) | F3: RRP | G3: ALR, DHI | H3: 0 | I3: H1-H2 | L3: Open | O3: Need confirmation with JBG | S3: =IF(Project_Tracker[[#This Row],[Project Lead]]="", "", IFERROR(VLOOKUP(Project_Tracker[[#This Row],[Project Lead]], Setting!C:D, 2, 0), "")) -> ratih_putri@banpuindo.co.id | U3: =Project_Tracker[[#This Row],[Project Lead]]&", "&Project_Tracker[[#This Row],[Team Collaboration]] -> RRP, ALR, DHI | AC3: 2025
A4: 3 | B4: Management System | C4: ITM Integrated Management System (TIMES) Establishment -Site Level | D4: MS 1.3 | E4: TIMES QMS - TRUST (Establishment) | F4: ARS | G4: ALR, DHI, RRP | H4: 0 | I4: Q3-H2 | L4: Open | O4: Still waiting key deliverables of Katulistiwa Project | S4: =IF(Project_Tracker[[#This Row],[Project Lead]]="", "", IFERROR(VLOOKUP(Project_Tracker[[#This Row],[Project Lead]], Setting!C:D, 2, 0), "")) -> aditya_r@banpuindo.co.id | U4: =Project_Tracker[[#This Row],[Project Lead]]&", "&Project_Tracker[[#This Row],[Team Collaboration]] -> ARS, ALR, DHI, RRP | AC4: 2025
A5: 4 | B5: Management System | C5: ITM Integrated Management System (TIMES) Element/Standard Deployment | D5: MS 2.1 | E5: Strategy & Performance Management | F5: ALR | H5: 1 | I5: 45838 | J5: 45474 | K5: 45838 | L5: Completed | M5: 1. Already identified the requirements for the Management Standards 2. Already drafted for the Management Standard 3. Already Followed-up the 1st review result from PO 4. Conduct 2nd review from MSBP Head 5. Conduct 3rd review from ERSM Head 6. Conduct Alignment Meeting with related stakeholders in Subsidiaries 7. Finetune the Management Standard Document | N5: 1. Conduct the approval for the MS Documents | O5: N/A | P5: =Project_Tracker[[#This Row],[End Date]]-Project_Tracker[[#This Row],[Target Date]] -> 0 | S5: =IF(Project_Tracker[[#This Row],[Project Lead]]="", "", IFERROR(VLOOKUP(Project_Tracker[[#This Row],[Project Lead]], Setting!C:D, 2, 0), "")) -> aldy_rienaldy@banpuindo.co.id | U5: =Project_Tracker[[#This Row],[Project Lead]]&", "&Project_Tracker[[#This Row],[Team Collaboration]] -> ALR, | AC5: 2025
A6: 5 | B6: Management System | C6: ITM Integrated Management System (TIMES) Element/Standard Deployment | D6: MS 2.2 | E6: TIMES QAR/Auditing Management | F6: RRP | G6: ALR | H6: 0.9 | I6: Q2-H1 | L6: Progress | M6: 1. Already reviewed MS Auditing Management that already updated by Excellence Team to be MS Assurance Management System 2. Already communicate Detail Context of Management Standard to DSPM/SPM/MS & HSEC/CD all sites on 7 May 2025 | N6: 1. Communicate Management Standard to Site Management and Function Head Related all sites 2. Getting approval MS Document | S6: =IF(Project_Tracker[[#This Row],[Project Lead]]="", "", IFERROR(VLOOKUP(Project_Tracker[[#This Row],[Project Lead]], Setting!C:D, 2, 0), "")) -> ratih_putri@banpuindo.co.id | U6: =Project_Tracker[[#This Row],[Project Lead]]&", "&Project_Tracker[[#This Row],[Team Collaboration]] -> RRP, ALR | AC6: 2025
A7: 7 | B7: Management System | C7: ITM Integrated Management System (TIMES) Element/Standard Deployment | D7: MS 2.4 | E7: ESG | F7: ALR | G7: ASN, RRP | H7: 1 | I7: 46022 | J7: 45537 | K7: 46022 | L7: Completed | M7: 1. Already showed to SD regarding ESG ownership mapping to the Business Process 2. Already reviewed the mapping result 3. Already conducted the Kick-Off Meeting 4. Already explained to SD PO regarding TIMES 5. Identify the ESG Priority (Requirement to be set-up for the governance pointing to BP) in 2025 6. Already developed the ESG requirements based on ESG Topics 7. Already reviewed all ESG Requirements based on ESG Sub Topics 8. Already mapped the priority requirement to the Business Process (as the ownership) 9. Already set up the roadmap 10. Finetuning communication materials 11. Plan the Communication Strategy | N7: 1. Present the Roadmap to the related stakeholders 2. Finetuning the review results for the roadmap 3. Present the roadmap and initiative for the 2nd Phase | O7: N/A | P7: =Project_Tracker[[#This Row],[End Date]]-Project_Tracker[[#This Row],[Target Date]] -> 0 | S7: =IF(Project_Tracker[[#This Row],[Project Lead]]="", "", IFERROR(VLOOKUP(Project_Tracker[[#This Row],[Project Lead]], Setting!C:D, 2, 0), "")) -> aldy_rienaldy@banpuindo.co.id | U7: =Project_Tracker[[#This Row],[Project Lead]]&", "&Project_Tracker[[#This Row],[Team Collaboration]] -> ALR, ASN, RRP | AC7: 2025
A8: 8 | B8: Management System | C8: ITM Integrated Management System (TIMES) Element/Standard Deployment | D8: MS 2.5 | E8: Security Management (ITM + SITES) | F8: ARS | G8: DHI | H8: 1 | I8: Q2-H1 | L8: Completed | M8: Policy and Management Standard still on review by MSBP Head | N8: To align SOP on ITM Level with Site level | S8: =IF(Project_Tracker[[#This Row],[Project Lead]]="", "", IFERROR(VLOOKUP(Project_Tracker[[#This Row],[Project Lead]], Setting!C:D, 2, 0), "")) -> aditya_r@banpuindo.co.id | U8: =Project_Tracker[[#This Row],[Project Lead]]&", "&Project_Tracker[[#This Row],[Team Collaboration]] -> ARS, DHI | AC8: 2025
A9: 9 | B9: Management System | C9: ITM Integrated Management System (TIMES) Element/Standard Deployment | D9: MS 2.6 | E9: Management Review (MR) | F9: ALR | G9: RRP | H9: 0.85 | I9: 45838 | J9: 45474 | K9: 45838 | L9: Progress | M9: 1. Already developed the Management Standard (MR) | N9: 1. Conduct communication and alignment meeting with Counterpart 2. Finetune and Approval | O9: N/A | P9: =Project_Tracker[[#This Row],[End Date]]-Project_Tracker[[#This Row],[Target Date]] -> 0 | S9: =IF(Project_Tracker[[#This Row],[Project Lead]]="", "", IFERROR(VLOOKUP(Project_Tracker[[#This Row],[Project Lead]], Setting!C:D, 2, 0), "")) -> aldy_rienaldy@banpuindo.co.id | U9: =Project_Tracker[[#This Row],[Project Lead]]&", "&Project_Tracker[[#This Row],[Team Collaboration]] -> ALR, RRP | AC9: 2025
A10: 10 | B10: Management System | C10: ITM Integrated Management System (TIMES) Element/Standard Deployment | D10: MS 2.7 | E10: Community Development | F10: DHI | G10: ALR | H10: 0 | I10: 45838 | L10: Hold | S10: =IF(Project_Tracker[[#This Row],[Project Lead]]="", "", IFERROR(VLOOKUP(Project_Tracker[[#This Row],[Project Lead]], Setting!C:D, 2, 0), "")) -> dhany_indraswara@banpuindo.co.id | U10: =Project_Tracker[[#This Row],[Project Lead]]&", "&Project_Tracker[[#This Row],[Team Collaboration]] -> DHI, ALR | AC10: 2025
A11: 11 | B11: Management System | C11: ITM Integrated Management System (TIMES) Element/Standard Deployment | D11: MS 2.8 | E11: Procurement/SCM | F11: ALR | G11: RRP | H11: 1 | I11: 45838 | J11: 45590 | K11: 45838 | L11: Completed | M11: 1. Already confirmed the project objective and scope 2. Aleady identified the requirements for Procedure Development 3. Already draft the Management Standard Documents 4. Already developed other requirements for Management Standard (collaborate with PO) 5. Alignment with Mahakam Leading Practice 6. Conduct alignment with Legal regarding contract 7. Done for final review and finalization of Management Standard | N11: 1. Conduct sircular approval of documents | O11: N/A | P11: =Project_Tracker[[#This Row],[End Date]]-Project_Tracker[[#This Row],[Target Date]] -> 0 | S11: =IF(Project_Tracker[[#This Row],[Project Lead]]="", "", IFERROR(VLOOKUP(Project_Tracker[[#This Row],[Project Lead]], Setting!C:D, 2, 0), "")) -> aldy_rienaldy@banpuindo.co.id | U11: =Project_Tracker[[#This Row],[Project Lead]]&", "&Project_Tracker[[#This Row],[Team Collaboration]] -> ALR, RRP | AC11: 2025
A12: 12 | B12: Management System | C12: ITM Integrated Management System (TIMES) Element/Standard Deployment | D12: MS 2.9 | E12: Change Management | F12: RRP | G12: ASN | H12: 0 | I12: H1-H2 | L12: Open | S12: =IF(Project_Tracker[[#This Row],[Project Lead]]="", "", IFERROR(VLOOKUP(Project_Tracker[[#This Row],[Project Lead]], Setting!C:D, 2, 0), "")) -> ratih_putri@banpuindo.co.id | U12: =Project_Tracker[[#This Row],[Project Lead]]&", "&Project_Tracker[[#This Row],[Team Collaboration]] -> RRP, ASN | AC12: 2025
A13: 13 | B13: Management System | C13: ITM Integrated Management System (TIMES) Element/Standard Deployment | D13: MS 2.1 | E13: Information Technology | F13: DHI | G13: ARS | H13: 0 | I13: 46015 | L13: Open | O13: Waiting IT organization establishment | S13: =IF(Project_Tracker[[#This Row],[Project Lead]]="", "", IFERROR(VLOOKUP(Project_Tracker[[#This Row],[Project Lead]], Setting!C:D, 2, 0), "")) -> dhany_indraswara@banpuindo.co.id | U13: =Project_Tracker[[#This Row],[Project Lead]]&", "&Project_Tracker[[#This Row],[Team Collaboration]] -> DHI, ARS | AC13: 2025
A14: 14 | B14: Management System | D14: MS 3 | E14: Management System Communication | F14: ALR | G14: ARS, RRP, DHI | H14: 1 | I14: 46021 | J14: 45689 | K14: 46021 | L14: Completed | M14: 1. Already drafted for the MOTION Agenda 2. Aleady conducted discussion with peers regarding draft of MOTION Agenda 3. Already informed the Motion Plan Series update to MSBP Head 4. Already send the 3rd Motion Series | N14: 1. Implement for regular motion agenda | O14: N/A | P14: =Project_Tracker[[#This Row],[End Date]]-Project_Tracker[[#This Row],[Target Date]] -> 0 | S14: =IF(Project_Tracker[[#This Row],[Project Lead]]="", "", IFERROR(VLOOKUP(Project_Tracker[[#This Row],[Project Lead]], Setting!C:D, 2, 0), "")) -> aldy_rienaldy@banpuindo.co.id | U14: =Project_Tracker[[#This Row],[Project Lead]]&", "&Project_Tracker[[#This Row],[Team Collaboration]] -> ALR, ARS, RRP, DHI | AC14: 2025
A15: 15 | B15: Management System | D15: MS 4 | E15: ITM Business Process Highlevel and its implementation | F15: ASN | G15: ALR, ARS, RRP, DHI | H15: 0.95 | I15: Q2-H1 | J15: 45699 | K15: 45777 | L15: Progress | M15: Actual project completion (80%) is calculated as of April 29th, 2025. - Most project activities in the tenth week have been focused on Conducting workshops, Gathering additional inputs and data, Discussed with workshop - All workshops are currently in completed - The current progressing tasks include target operating model design (70%). - Follow-up for Final Outcomes and preparation SteerCo and Sponsor Meeting. | S15: =IF(Project_Tracker[[#This Row],[Project Lead]]="", "", IFERROR(VLOOKUP(Project_Tracker[[#This Row],[Project Lead]], Setting!C:D, 2, 0), "")) -> andri_s@banpuindo.co.id | U15: =Project_Tracker[[#This Row],[Project Lead]]&", "&Project_Tracker[[#This Row],[Team Collaboration]] -> ASN, ALR, ARS, RRP, DHI | AC15: 2025
A16: 16 | B16: Management System | C16: BP-Organization Alignment and QMS as aggreed planned (based on the poin 4) | D16: MS 5.1 | E16: Finance & Accounting | F16: ALR | G16: ARS | H16: 1 | I16: 45670 | J16: 45461 | K16: 45670 | L16: Completed | M16: 1. Already developed BP L2-3 FA 2. Already developed Detail Flow Process + RASCI 3. Already reviewed BP & Flow Process by Process Owner 4. Already conducted BP review with Finance Director 5. Already designed the propose Organization Structure (with HR) 6. Already sent Project Closing + Deliverables to related stakeholders | N16: 1. Conduct Approval on BP Design (Waiting HRMC Results) | O16: N/A | P16: =Project_Tracker[[#This Row],[End Date]]-Project_Tracker[[#This Row],[Target Date]] -> 0 | S16: =IF(Project_Tracker[[#This Row],[Project Lead]]="", "", IFERROR(VLOOKUP(Project_Tracker[[#This Row],[Project Lead]], Setting!C:D, 2, 0), "")) -> aldy_rienaldy@banpuindo.co.id | U16: =Project_Tracker[[#This Row],[Project Lead]]&", "&Project_Tracker[[#This Row],[Team Collaboration]] -> ALR, ARS | AC16: 2025
A17: 17 | B17: Management System | C17: BP-Organization Alignment and QMS as aggreed planned (based on the poin 4) | D17: MS 5.2 | E17: JBG Pre-Closure and MineClosure | F17: RRP | G17: ALR | H17: 1 | I17: Q1-H1 | L17: Completed | M17: 1. Already develop BP Level 0,1,2 Pre Closure and Mine Closure Version in Visio Format 2. Organization Structure Process by HR | S17: =IF(Project_Tracker[[#This Row],[Project Lead]]="", "", IFERROR(VLOOKUP(Project_Tracker[[#This Row],[Project Lead]], Setting!C:D, 2, 0), "")) -> ratih_putri@banpuindo.co.id | U17: =Project_Tracker[[#This Row],[Project Lead]]&", "&Project_Tracker[[#This Row],[Team Collaboration]] -> RRP, ALR | AC17: 2025
A18: 18 | B18: Management System | C18: BP-Organization Alignment and QMS as aggreed planned (based on the poin 4) | D18: MS 5.3 | E18: ITM Campus | F18: ARS | G18: DHI | H18: 0.5 | I18: Q1-H1 | L18: Open | O18: Need confirmation with HR (Aligned with Khatulistiwa) | S18: =IF(Project_Tracker[[#This Row],[Project Lead]]="", "", IFERROR(VLOOKUP(Project_Tracker[[#This Row],[Project Lead]], Setting!C:D, 2, 0), "")) -> aditya_r@banpuindo.co.id | U18: =Project_Tracker[[#This Row],[Project Lead]]&", "&Project_Tracker[[#This Row],[Team Collaboration]] -> ARS, DHI | AC18: 2025
A19: 19 | B19: Management System | C19: BP-Organization Alignment and QMS as aggreed planned (based on the poin 4) | D19: MS 5.4 | E19: Corporate Secretary and Legal | F19: RRP | G19: ARS | H19: 1 | I19: Q2-H1 | L19: Completed | M19: 1. Already develop BP Level 1,2, Flow Process Detail, and RASCI Summary for Corsec and Legal 2. Already sent the BP document to HR and Corsec Legal team 3. Already joined Kick Off Meeting with Korn Ferry and team 4. Support KF Team regarding some concern related BP and RASCI 5. Sharing how to develop BP and Flow Process based on ITM Standard to KF Team 6. Prepare BP analyze and reccomendation for Record Management 7. Facilitate process owner to review BP and Flow Process to decide using KF version or ITM version 8. Monitor and tracking progress of BP and Flow Process completion that delivered by KF 9. Facilitate process owner to review BP outstanding (Litigation, IPR, Record Management) 10. Confirmation to PO for reviewing update BP from KF | S19: =IF(Project_Tracker[[#This Row],[Project Lead]]="", "", IFERROR(VLOOKUP(Project_Tracker[[#This Row],[Project Lead]], Setting!C:D, 2, 0), "")) -> ratih_putri@banpuindo.co.id | U19: =Project_Tracker[[#This Row],[Project Lead]]&", "&Project_Tracker[[#This Row],[Team Collaboration]] -> RRP, ARS | AC19: 2025
A20: 20 | B20: Management System | C20: BP-Organization Alignment and QMS as aggreed planned (based on the poin 4) | D20: MS 5.5 | E20: Information Technology | F20: DHI | G20: ARS | H20: 1 | I20: 45681 | J20: 45658 | K20: 45681 | L20: Completed | M20: -already develop operating model - already develop BP LVL 1 IT Division - Already develop BP LVL 2 DATA & AI - Already develop BP LVL 2 Governance & Assurance - Already develop BP LVL 2 Strategy & Architect - Already Develop BP LVL 2 Service & Infra - Already Develop BP LVL 2 IT Development & Implementation | N20: BP Approval Process | O20: N/A | P20: =Project_Tracker[[#This Row],[End Date]]-Project_Tracker[[#This Row],[Target Date]] -> 0 | S20: =IF(Project_Tracker[[#This Row],[Project Lead]]="", "", IFERROR(VLOOKUP(Project_Tracker[[#This Row],[Project Lead]], Setting!C:D, 2, 0), "")) -> dhany_indraswara@banpuindo.co.id | U20: =Project_Tracker[[#This Row],[Project Lead]]&", "&Project_Tracker[[#This Row],[Team Collaboration]] -> DHI, ARS | AC20: 2025
A21: 21 | B21: Management System | C21: BP-Organization Alignment and QMS as aggreed planned (based on the poin 4) | D21: MS 5.6 | E21: MSBP | F21: ALR | G21: ARS, RRP, DHI, RSW, BEY | H21: 0.73 | I21: 45930 | J21: 45323 | K21: 45930 | L21: Progress | M21: 1. Already developed BP L2-3 MS, BP, CM, CI 2. Already developed Detail Flow Process + RASCI 3. Already identified the required governance 4. Already drafted for several SOP related MS, BP, CM, CI 5. Already conducted discussion with MSBP Head regarding project timeline and scope 6. Already completed for MS SOP | N21: 1. Continue Review Serial SOP of MSBP 2. Monitor for CI Governance development 3. Continue develop for MS Document in Management System Area | O21: N/A | P21: =Project_Tracker[[#This Row],[End Date]]-Project_Tracker[[#This Row],[Target Date]] -> 0 | S21: =IF(Project_Tracker[[#This Row],[Project Lead]]="", "", IFERROR(VLOOKUP(Project_Tracker[[#This Row],[Project Lead]], Setting!C:D, 2, 0), "")) -> aldy_rienaldy@banpuindo.co.id | U21: =Project_Tracker[[#This Row],[Project Lead]]&", "&Project_Tracker[[#This Row],[Team Collaboration]] -> ALR, ARS, RRP, DHI, RSW, BEY | AC21: 2025
A22: 22 | B22: Management System | C22: BP-Organization Alignment and QMS as aggreed planned (based on the poin 4) | D22: MS 5.7 | E22: Coal Sales & Trading | F22: RRP | G22: ARS | H22: 1 | I22: Q2-H1 | L22: Completed | M22: 1. Drafting Project Charter 2. Conduct Kick Off Meeting on 24 July 2025 3. Review Current Business Process for Domestic Sales, SCQM, Sales Logistic Services, and Coal Trading 4. Develop CST Business Process Level 1-3 5. Conduct internal alignment meeting 6. Send update progress report 7. Wrap up summary and reccomendation | S22: =IF(Project_Tracker[[#This Row],[Project Lead]]="", "", IFERROR(VLOOKUP(Project_Tracker[[#This Row],[Project Lead]], Setting!C:D, 2, 0), "")) -> ratih_putri@banpuindo.co.id | U22: =Project_Tracker[[#This Row],[Project Lead]]&", "&Project_Tracker[[#This Row],[Team Collaboration]] -> RRP, ARS | AC22: 2025
A23: 23 | B23: Management System | C23: BP-Organization Alignment and QMS as aggreed planned (based on the poin 4) | D23: MS 5.8 | E23: Melak Cluster Enhancement | F23: ALR | G23: ARS, RRP, DHI | H23: 0.79 | I23: 45838 | J23: 45708 | K23: 45838 | L23: Progress | M23: 1. Already conducted Stage 1 (BP Workshop) 2. Already conducted Stage 2 (MS Workshop) 3. Already conducted review and alignment for the BP Design 4. Already coordinate and remind target with DSPM - for operational basis in SOP development 5. Already conducted further discussion regarding Coal Processing process - align with IBU 6. Already conducted socialization agenda to All TCM-BEK related stakeholders regarding BP Level 0 Mapping 7. Already continued the project by giving the TCM & BEK BP to Consultant Team 8. Already ensure and monitor the implementation of MELAK BP Development by Consultant Team | N23: 1. Need to Finalize the ITM High Level Business Process 2. Ensure the socialization of the final deliverables of MELAK BP to all MELAK respective stakeholders 3. Implement the next phase of Governance development | O23: N/A | P23: =Project_Tracker[[#This Row],[End Date]]-Project_Tracker[[#This Row],[Target Date]] -> 0 | S23: =IF(Project_Tracker[[#This Row],[Project Lead]]="", "", IFERROR(VLOOKUP(Project_Tracker[[#This Row],[Project Lead]], Setting!C:D, 2, 0), "")) -> aldy_rienaldy@banpuindo.co.id | U23: =Project_Tracker[[#This Row],[Project Lead]]&", "&Project_Tracker[[#This Row],[Team Collaboration]] -> ALR, ARS, RRP, DHI | AC23: 2025
A24: 24 | B24: Management System | C24: BP-Organization Alignment and QMS as aggreed planned (based on the poin 4) | D24: MS 5.9 | E24: IEU | F24: RRP | G24: ALR | H24: 0.2 | I24: Q3-H2 | L24: Hold | O24: Still waiting key deliverables of Katulistiwa Project | S24: =IF(Project_Tracker[[#This Row],[Project Lead]]="", "", IFERROR(VLOOKUP(Project_Tracker[[#This Row],[Project Lead]], Setting!C:D, 2, 0), "")) -> ratih_putri@banpuindo.co.id | U24: =Project_Tracker[[#This Row],[Project Lead]]&", "&Project_Tracker[[#This Row],[Team Collaboration]] -> RRP, ALR | AC24: 2025
A25: 25 | B25: Management System | C25: BP-Organization Alignment and QMS as aggreed planned (based on the poin 4) | D25: MS 5.1 | E25: TRUST (BP & Organization) | F25: ARS | G25: ALR, DHI, RRP | H25: 0 | I25: Q3-H2 | L25: Open | M25: Waiting for ITM & Melak Operating Model and Business Process Enhancement | O25: Still waiting key deliverables of Katulistiwa Project | S25: =IF(Project_Tracker[[#This Row],[Project Lead]]="", "", IFERROR(VLOOKUP(Project_Tracker[[#This Row],[Project Lead]], Setting!C:D, 2, 0), "")) -> aditya_r@banpuindo.co.id | U25: =Project_Tracker[[#This Row],[Project Lead]]&", "&Project_Tracker[[#This Row],[Team Collaboration]] -> ARS, ALR, DHI, RRP | AC25: 2025
A26: 26 | B26: Management System | C26: BP-Organization Alignment and QMS as aggreed planned (based on the poin 4) | D26: MS 5.11 | E26: Port Organization (New Business)/IBU | F26: ARS | G26: DHI | H26: 0.85 | I26: Q4-H2 | J26: 45677 | K26: 46021 | L26: Progress | M26: 1. BP Lvl 0 IBU & Logistic has developed 2. BP Lvl 1-2 IBU & Logistic has developed 3. BP Lvl 3 IBU & Logistic 85% developed 4. Waiting for IBU & Logistic business structure (Sub Holding) | N26: Still waiting key deliverables of Katulistiwa Project, prepare DOA Identification Matrix for Interim and Operational, Confirmation DOA from Coal Trading for Quaotation to customer | S26: =IF(Project_Tracker[[#This Row],[Project Lead]]="", "", IFERROR(VLOOKUP(Project_Tracker[[#This Row],[Project Lead]], Setting!C:D, 2, 0), "")) -> aditya_r@banpuindo.co.id | U26: =Project_Tracker[[#This Row],[Project Lead]]&", "&Project_Tracker[[#This Row],[Team Collaboration]] -> ARS, DHI | AC26: 2025
A27: 28 | B27: Management System | C27: BP-Organization Alignment and QMS as aggreed planned (based on the poin 4) | D27: MS 5.13 | E27: BP-Organization Alignment and QMS as aggreed planned (based on the poin 4) | F27: ALR | G27: DHI | H27: 1 | I27: 45852 | J27: 45719 | K27: 45852 | L27: Completed | M27: 1. Already confirmed the project objective and scope 2. Conduct Kick-Off Meeting 3. Finalized SIPOC Table 4. Developed FSP BP, Identify PPI 5. Already develop Flow Process + RASCI (18/18) 6. Identified the requirements for Procedure Development 7. Already developed Procedure and Derivative (SOP)* 8. Review and Finalization of Procedure | N27: 1. Conduct sircular approval of documents | P27: =Project_Tracker[[#This Row],[End Date]]-Project_Tracker[[#This Row],[Target Date]] -> 0 | S27: =IF(Project_Tracker[[#This Row],[Project Lead]]="", "", IFERROR(VLOOKUP(Project_Tracker[[#This Row],[Project Lead]], Setting!C:D, 2, 0), "")) -> aldy_rienaldy@banpuindo.co.id | U27: =Project_Tracker[[#This Row],[Project Lead]]&", "&Project_Tracker[[#This Row],[Team Collaboration]] -> ALR, DHI | AC27: 2025
A28: 29 | B28: Management System | C28: BP-Organization Alignment and QMS as aggreed planned (based on the poin 4) | D28: MS 5.14 | E28: Community Development (Process & System) | F28: DHI | G28: ALR | H28: 0 | I28: 45838 | L28: Hold | S28: =IF(Project_Tracker[[#This Row],[Project Lead]]="", "", IFERROR(VLOOKUP(Project_Tracker[[#This Row],[Project Lead]], Setting!C:D, 2, 0), "")) -> dhany_indraswara@banpuindo.co.id | U28: =Project_Tracker[[#This Row],[Project Lead]]&", "&Project_Tracker[[#This Row],[Team Collaboration]] -> DHI, ALR | AC28: 2025
A29: 31 | B29: Management System | C29: BP-Organization Alignment and QMS as aggreed planned (based on the poin 4) | D29: MS 5.16 | E29: IBO Enhancement | F29: RRP | G29: ALR | H29: 0.1 | I29: Q2-H1 | L29: Hold | M29: - Conduct follow up discussion - Share project overvier template - Encourage to provide Business Canvas Model as Strategic Context PT IBO | O29: Still waiting key deliverables of Katulistiwa Project | S29: =IF(Project_Tracker[[#This Row],[Project Lead]]="", "", IFERROR(VLOOKUP(Project_Tracker[[#This Row],[Project Lead]], Setting!C:D, 2, 0), "")) -> ratih_putri@banpuindo.co.id | U29: =Project_Tracker[[#This Row],[Project Lead]]&", "&Project_Tracker[[#This Row],[Team Collaboration]] -> RRP, ALR | AC29: 2025
A30: 32 | B30: Management System | C30: BP-Organization Alignment and QMS as aggreed planned (based on the poin 4) | D30: MS 5.17 | E30: SCM Project (Mahakam Project) | F30: ARS | G30: ALR, RRP, DHI | H30: 0.85 | I30: H1-H2 | L30: Progress | M30: Workshop Offline To-Be Process Aligned with all PO already conducted at IBO | N30: Develop standard procedure for SCM process | S30: =IF(Project_Tracker[[#This Row],[Project Lead]]="", "", IFERROR(VLOOKUP(Project_Tracker[[#This Row],[Project Lead]], Setting!C:D, 2, 0), "")) -> aditya_r@banpuindo.co.id | U30: =Project_Tracker[[#This Row],[Project Lead]]&", "&Project_Tracker[[#This Row],[Team Collaboration]] -> ARS, ALR, RRP, DHI | AC30: 2025
A31: 32 | B31: Management System | C31: BP-Organization Alignment and QMS as aggreed planned (based on the poin 4) | D31: MS 5.17 | E31: SCM Project (as Transformation Team) | F31: ALR | G31: ARS, RRP, DHI | H31: 1 | I31: H1-H2 | L31: Completed | M31: 1. Already confirmed the project objective and scope 2. Conduct Kick-Off Meeting 3. Identified the requirements for Procedure Development 4. Already developed Procedure and Derivative (SOP)* 5. Review and Finalization of Procedure | N31: 1. Conduct sircular approval of documents | AC31: 2025
A32: 33 | B32: Management System | C32: BP-Organization Alignment and QMS as aggreed planned (based on the poin 4) | D32: MS 5.18 | E32: OS - Q P B Plan & Revision (MS & SOP) | F32: ARS | H32: 0.8 | I32: Q2-H1 | J32: 45684 | K32: 46019 | L32: Progress | M32: 1. SOP for QPB revision already developed 2. SOP for QBP Actual already drafted | N32: Develop Management Standard for QPB Process | S32: =IF(Project_Tracker[[#This Row],[Project Lead]]="", "", IFERROR(VLOOKUP(Project_Tracker[[#This Row],[Project Lead]], Setting!C:D, 2, 0), "")) -> aditya_r@banpuindo.co.id | U32: =Project_Tracker[[#This Row],[Project Lead]]&", "&Project_Tracker[[#This Row],[Team Collaboration]] -> ARS, | AC32: 2025
A33: 34 | B33: Management System | C33: BP-Organization Alignment and QMS as aggreed planned (based on the poin 4) | D33: MS 5.19 | E33: Contractor Management & Engineering Enhancement (BP) | F33: ARS | H33: 1 | I33: Q2-H1 | J33: 45663 | K33: 45743 | L33: Completed | M33: 1. BP Lvl 1-2 CMEE has developed 2. BP Lvl 3 (detail flow) has developed 3. SP for Contractor Type has developed | S33: =IF(Project_Tracker[[#This Row],[Project Lead]]="", "", IFERROR(VLOOKUP(Project_Tracker[[#This Row],[Project Lead]], Setting!C:D, 2, 0), "")) -> aditya_r@banpuindo.co.id | U33: =Project_Tracker[[#This Row],[Project Lead]]&", "&Project_Tracker[[#This Row],[Team Collaboration]] -> ARS, | AC33: 2025
A34: 35 | B34: Management System | C34: BP-Organization Alignment and QMS as aggreed planned (based on the poin 4) | D34: MS 5.20 | E34: ITMP Phase 3 | F34: ARS | H34: 0 | I34: Q2-H1 | L34: Open | S34: =IF(Project_Tracker[[#This Row],[Project Lead]]="", "", IFERROR(VLOOKUP(Project_Tracker[[#This Row],[Project Lead]], Setting!C:D, 2, 0), "")) -> aditya_r@banpuindo.co.id | U34: =Project_Tracker[[#This Row],[Project Lead]]&", "&Project_Tracker[[#This Row],[Team Collaboration]] -> ARS, | AC34: 2025
A35: 36 | B35: Management System | C35: Facilitating Digital Project on Standardization/Formalization (Aligned with Digital Initiatives) as collaborated with Innovation Team | D35: MS 6.1 | E35: Invoice Management System | F35: ALR | G35: BEY | H35: 0 | I35: H1-H2 | L35: Open | S35: =IF(Project_Tracker[[#This Row],[Project Lead]]="", "", IFERROR(VLOOKUP(Project_Tracker[[#This Row],[Project Lead]], Setting!C:D, 2, 0), "")) -> aldy_rienaldy@banpuindo.co.id | U35: =Project_Tracker[[#This Row],[Project Lead]]&", "&Project_Tracker[[#This Row],[Team Collaboration]] -> ALR, BEY | AC35: 2025
A36: 37 | B36: Management System | C36: Facilitating Digital Project on Standardization/Formalization (Aligned with Digital Initiatives) as collaborated with Innovation Team | D36: MS 6.2 | E36: Melak Integrated Mine Planning | F36: ALR | G36: AFZ | H36: 1 | I36: H1-H2 | L36: Completed | M36: 1. Already draft BP as Khatulistiwa Project Result 2. Clarify and Validate BP LOMP & 5YRP 3. Clarify and Validate BP Annual Planning 4. Clarify and Validate BP 3MRP & Monthly Planning 5. Done for Alignment with OS, MED, ERSM, HSEC, CBIC 6. Done for RASCI Development | N36: 1. Confirm the RASCI and OD with HR | S36: =IF(Project_Tracker[[#This Row],[Project Lead]]="", "", IFERROR(VLOOKUP(Project_Tracker[[#This Row],[Project Lead]], Setting!C:D, 2, 0), "")) -> aldy_rienaldy@banpuindo.co.id | U36: =Project_Tracker[[#This Row],[Project Lead]]&", "&Project_Tracker[[#This Row],[Team Collaboration]] -> ALR, AFZ | AC36: 2025
A37: 38 | B37: Management System | C37: Facilitating Digital Project on Standardization/Formalization (Aligned with Digital Initiatives) as collaborated with Innovation Team | D37: MS 6.3 | E37: SSO – Blending Optimization | F37: ARS | G37: ALR, RSW | H37: 0.9 | I37: 45925 | J37: 45839 | K37: 46009 | L37: Progress | M37: Already set up role play and alignment with all stakeholders for SOP SSO | N37: To revise and finalize SOP SSO according to role play result | S37: =IF(Project_Tracker[[#This Row],[Project Lead]]="", "", IFERROR(VLOOKUP(Project_Tracker[[#This Row],[Project Lead]], Setting!C:D, 2, 0), "")) -> aditya_r@banpuindo.co.id | U37: =Project_Tracker[[#This Row],[Project Lead]]&", "&Project_Tracker[[#This Row],[Team Collaboration]] -> ARS, ALR, RSW | AC37: 2025
A38: 40 | B38: Management System | C38: Facilitating Digital Project on Standardization/Formalization (Aligned with Digital Initiatives) as collaborated with Innovation Team | D38: MS 6.5 | E38: Data Governance (3 Project) - Master Data (OS Project) - Coal Inventory - ITM Data Governance for OS Project | F38: DHI | G38: AFZ | H38: 1 | I38: 45838 | J38: 45720 | K38: 45808 | L38: Completed | M38: -Build WBS for the rest of project -Study the data governance document - Get the details of activity WBS for MSBP task -Already develop project charter -'-As-Is process analysis & Gap Analysis 'Doing sprint implement for all project - Master Data (OS Project) - Coal Inventory - ITM Data Governance for OS Project POC Activity for truck scale project | N38: -Approval document ITM (Fully Approved) & BEK -Adoption Process (Training, Communication, Utilization for TS) | S38: =IF(Project_Tracker[[#This Row],[Project Lead]]="", "", IFERROR(VLOOKUP(Project_Tracker[[#This Row],[Project Lead]], Setting!C:D, 2, 0), "")) -> dhany_indraswara@banpuindo.co.id | U38: =Project_Tracker[[#This Row],[Project Lead]]&", "&Project_Tracker[[#This Row],[Team Collaboration]] -> DHI, AFZ | AC38: 2025
B39: Management System | C39: Facilitating Digital Project on Standardization/Formalization (Aligned with Digital Initiatives) as collaborated with Innovation Team | D39: MS 6.6 | E39: Tug Management System Standardization | F39: DHI | G39: AFZ | H39: 1 | I39: 45869 | J39: 45782 | K39: 45808 | L39: Completed | M39: -Already initial meeting with SC team '-Detail meeting to get details target -Details deliverables project for prodedure (TMS Charter) -Already build 5 Business Process flow based on system analysis. -- Need to clarify & Discuss with PO to get the final business process flow -Build SOP for new process flow (6 SOP + 2 WI) | N39: - Continue the activity with pak chrisna weekly SOP Barge Operation Compliance -> Review Pak Chrisna STS Transhipment -> Review pak Chrisna WI: Shipper Representative -> Approval Guideline TMS -> Tug & Boat owner & Master (By Manual book) | S39: =IF(Project_Tracker[[#This Row],[Project Lead]]="", "", IFERROR(VLOOKUP(Project_Tracker[[#This Row],[Project Lead]], Setting!C:D, 2, 0), "")) -> dhany_indraswara@banpuindo.co.id | U39: =Project_Tracker[[#This Row],[Project Lead]]&", "&Project_Tracker[[#This Row],[Team Collaboration]] -> DHI, AFZ | AC39: 2025
B40: Management System | C40: Facilitating Digital Project on Standardization/Formalization (Aligned with Digital Initiatives) as collaborated with Innovation Team | D40: MS 6.7 | E40: Data Management for ITM Group Level | F40: DHI | G40: AFZ | H40: 1 | I40: 45991 | J40: 45782 | K40: 45808 | L40: Completed | M40: -Meeting with all stakeholder to get the insight -Build framework to guide the development -Analyze DAMA Box to standardize the system -Already build framework go build MS - Build WBS for detailed project - Build project charter (finalized) -'-Development MS ('- Build MS with process owner 2x/week) 8% - Policy Review | N40: -Final review with process owner (pak Amang & pak Muhardian) -Meet with HR & MSBP to build change culture klausul (reschedule)** | S40: =IF(Project_Tracker[[#This Row],[Project Lead]]="", "", IFERROR(VLOOKUP(Project_Tracker[[#This Row],[Project Lead]], Setting!C:D, 2, 0), "")) -> dhany_indraswara@banpuindo.co.id | U40: =Project_Tracker[[#This Row],[Project Lead]]&", "&Project_Tracker[[#This Row],[Team Collaboration]] -> DHI, AFZ | AC40: 2025
B41: Management System | C41: Facilitating Digital Project on Standardization/Formalization (Aligned with Digital Initiatives) as collaborated with Innovation Team | D41: MS 6.8 | E41: Barge Logistic Management System (BLMS) Standardization | F41: DHI | G41: ARS | H41: 1 | J41: 45782 | K41: 46022 | L41: Completed | M41: -Meeting with all stakeholder to get the insight -Build framework to guide the development -Already build Analysis process flow (01) '-Update new flow integration with TMS & blms (Already meeting with pak Eka & Putra) - -Update flow process on planning area integrated with barge optimizer & SSO application (Already meeting with pak Eka & Putra) -Still on progress for finalization | N41: Guideline BLMS -> All User | S41: =IF(Project_Tracker[[#This Row],[Project Lead]]="", "", IFERROR(VLOOKUP(Project_Tracker[[#This Row],[Project Lead]], Setting!C:D, 2, 0), "")) -> dhany_indraswara@banpuindo.co.id | U41: =Project_Tracker[[#This Row],[Project Lead]]&", "&Project_Tracker[[#This Row],[Team Collaboration]] -> DHI, ARS | AC41: 2025
A42: 41 | B42: Management System | C42: MSBP System Enhancement | D42: MS 7.1 | E42: TIMES CEPAT - IRS | F42: RRP | G42: ALR, AFZ | H42: 1 | I42: Q3-H2 | L42: Completed | M42: STAGE 1: TIMES CEPAT IRS 1. Prepare TIMES CEPAT sketch and requirement 2. Develop UI/UX 3. Conduct backlog grooming for Sprint 1 & 2 4. Kick off TIMES CEPAT on 26 February 2025 5. Sprint 1 Planning, Review, Retrospective 6. Sprint 2 Planning & finalization requirement for sprint 3. Review, Retrospective 7. Backlog Grooming before sprint planning 8. Detailing business value levers 9. . Sprint 3 Planning, Review, Retrospective 10. Sprint 4 Planning and development | N42: 1. Continue testing 2. Bug fixing 3. Prepare user manual 4. User Training 5. Go Live Communication | S42: =IF(Project_Tracker[[#This Row],[Project Lead]]="", "", IFERROR(VLOOKUP(Project_Tracker[[#This Row],[Project Lead]], Setting!C:D, 2, 0), "")) -> ratih_putri@banpuindo.co.id | U42: =Project_Tracker[[#This Row],[Project Lead]]&", "&Project_Tracker[[#This Row],[Team Collaboration]] -> RRP, ALR, AFZ | AC42: 2025
A43: 41 | B43: Management System | C43: MSBP System Enhancement | D43: MS 7.1 | E43: TIMES CEPAT - TIMES QAR | F43: RRP | G43: ALR, AFZ | H43: 0.95 | I43: Q3-H2 | L43: Progress | M43: 1. Prepare TIMES QAR Sketch & Requirement 2. Develop UI/UX TIMES QAR: Assurance Program & Assurance Plan (final) 3. Develop UI/UX TIMES QAR: Assurance Checklist (Self Assurance, Live Assurance, List of Finding) 4. Develop UI/UX TIMES QAR: Dashboard (All Subsidiary and Subsidiaries) 5. Develop UI/UX TIMES QAR: Detail NCR, Follow Up Action Plan & Result 6. Develop UI/UX TIMES CEPAT Setting: Reference Management 7. Develop UI/UX TIMES QAR Setting: Bank Checklist 8. Develop UI/UX TIMES QAR Setting: Assurance Program Table 10. Conduct weekly backlog grooming start from 5 May 2025 11. Conduct Pre Kick Off Meeting - Stage 2 TIMES CEPAT - TIMES QAR Development Project 12. Sprint 1-6 Planning, Development, Review, Retrospective | N43: Continue UAT, Prepare all setting (bank checklist, reference management, assurance program table, user management) | S43: =IF(Project_Tracker[[#This Row],[Project Lead]]="", "", IFERROR(VLOOKUP(Project_Tracker[[#This Row],[Project Lead]], Setting!C:D, 2, 0), "")) -> ratih_putri@banpuindo.co.id | AC43: 2025
A44: 41 | B44: Management System | C44: MSBP System Enhancement | D44: MS 7.1 | E44: TIMES CEPAT - NCR (STAGE 3) | F44: RRP | G44: ALR, AFZ | H44: 0.5 | I44: Q3-H2 | L44: Progress | M44: 1. Initial discussion regarding plan for stage 3 preparation 2. Conduct discussion with Project Sponsor to getting advice and endorsement 3. Prepare worksheet and confirmation schedule with site 4. Conduct getting feedback session with all sites | N44: Prepare requirement based on site user feedback, Prepare requirement for additional NCR source (asset risk survey) | O44: Due to budget & technical resources will be allocated to SMKP Development, so we need to hold technical development NCR Enhancement in 2025. | AC44: 2025
A45: 42 | B45: Management System | C45: MSBP System Enhancement | D45: MS 7.2 | E45: STONE/Document Repository Enhancement | F45: DHI | G45: ALR | H45: 1 | I45: 46001 | J45: 45670 | K45: 45747 | L45: Completed | M45: - Already meeting with IT div (Agung & Team) to get insight -'- Build WBS to get details of STONES details actiity - Allignment corsec legal (Record Management System) -List function head & email to get DCR pic '-Build details flow requirement with technical information to get insight from IT Team **Document action request flow **Approval flow Document perapihan -> Q3 Stones study melak for IT -> W3 W3 July -> Meet dengan IT solution from ITM stones '-Build matrix approval for all site - tune up requirement related to AI | N45: -Build new requirement for 2026 project -Already build Draft_01 user Interface/Experience -Continue buld UI/UX based on feedback team MID December FInal Requirement to IT 2x meet weekly | S45: =IF(Project_Tracker[[#This Row],[Project Lead]]="", "", IFERROR(VLOOKUP(Project_Tracker[[#This Row],[Project Lead]], Setting!C:D, 2, 0), "")) -> dhany_indraswara@banpuindo.co.id | U45: =Project_Tracker[[#This Row],[Project Lead]]&", "&Project_Tracker[[#This Row],[Team Collaboration]] -> DHI, ALR | AC45: 2025
A46: 43 | B46: Management System | C46: MSBP System Enhancement | D46: MS 7.3 | E46: ITM LEAP (ITM Lean Effective Activity Process) | F46: ARS | G46: DHI, ALR | H46: 0.3 | I46: H1-H2 | J46: 45777 | K46: 46022 | L46: Progress | M46: Already develop draft of prototype for LEAP on Microsoft 365 | N46: Continue develop LEAP prototype, Waiting for Khatulistiwa Project | S46: =IF(Project_Tracker[[#This Row],[Project Lead]]="", "", IFERROR(VLOOKUP(Project_Tracker[[#This Row],[Project Lead]], Setting!C:D, 2, 0), "")) -> aditya_r@banpuindo.co.id | U46: =Project_Tracker[[#This Row],[Project Lead]]&", "&Project_Tracker[[#This Row],[Team Collaboration]] -> ARS, DHI, ALR | AC46: 2025
A47: 44 | B47: Management System | C47: MSBP System Enhancement | D47: MS 7.4 | E47: MSBP Project Consolidation | F47: DHI | G47: ASN | H47: 1 | I47: 45678 | J47: 45670 | K47: 45678 | L47: Completed | M47: - Already build POC product of project tracker - Already develop database modeling - Already develop power BI dashboard - Already develop automate email - Already publish database, powerbi & power automate to production server | N47: Already develop all requirment on last meeting | O47: N/A | S47: =IF(Project_Tracker[[#This Row],[Project Lead]]="", "", IFERROR(VLOOKUP(Project_Tracker[[#This Row],[Project Lead]], Setting!C:D, 2, 0), "")) -> dhany_indraswara@banpuindo.co.id | U47: =Project_Tracker[[#This Row],[Project Lead]]&", "&Project_Tracker[[#This Row],[Team Collaboration]] -> DHI, ASN | AC47: 2025
A48: 45 | B48: Management System | C48: MSBP System Enhancement | D48: MS 7.5 | E48: CS Dashboard | F48: DHI | G48: ASN | H48: 1 | I48: 45673 | J48: 45670 | K48: 45673 | L48: Completed | M48: - Already build POC product of CS Dashboard - Already develop database modeling - Already develop power BI dashboard - Already publish database, powerbi & power automate to production server '- ReCheck database (KPI Items) - ReCheck Target on every KPI Items - Update details dashboard calculation & agregt - Final UAT all tools - Publish on prod server -'UAT with all user (Input data) | N48: -Waiting user input the data (CS Function Head) | O48: N/A | S48: =IF(Project_Tracker[[#This Row],[Project Lead]]="", "", IFERROR(VLOOKUP(Project_Tracker[[#This Row],[Project Lead]], Setting!C:D, 2, 0), "")) -> dhany_indraswara@banpuindo.co.id | U48: =Project_Tracker[[#This Row],[Project Lead]]&", "&Project_Tracker[[#This Row],[Team Collaboration]] -> DHI, ASN | AC48: 2025
A49: 46 | B49: Management System | C49: Management System and Facilitation | D49: MS 8.1 | E49: Facilitating on ISO 20000 | F49: ALR | G49: RRP | H49: 1 | I49: 45747 | J49: 45658 | K49: 45747 | L49: Completed | M49: 1. Already conducted for the Stage 1 (Facilitating the requirements fulfillment, internal audit, follow-up CAR Status) 2. Already conducted for the Stage 2 (Be Auditee for the external auditor event) 3. Already coordinated with IT Team for the next to do activities in ISO 20000 | N49: 1. Develop COE for Serial ISO 20000 preparation and Internal Audit 2. Communicate and review to respective stakeholders 3. State the Commitment | O49: N/A | P49: =Project_Tracker[[#This Row],[End Date]]-Project_Tracker[[#This Row],[Target Date]] -> 0 | S49: =IF(Project_Tracker[[#This Row],[Project Lead]]="", "", IFERROR(VLOOKUP(Project_Tracker[[#This Row],[Project Lead]], Setting!C:D, 2, 0), "")) -> aldy_rienaldy@banpuindo.co.id | U49: =Project_Tracker[[#This Row],[Project Lead]]&", "&Project_Tracker[[#This Row],[Team Collaboration]] -> ALR, RRP | AC49: 2025
A50: 47 | B50: Management System | C50: Management System and Facilitation | D50: MS 8.2 | E50: Internal Audit and MR for ISO 27001 and Upgrade | F50: ALR | G50: RRP | H50: 1 | I50: 45914 | J50: 45719 | K50: 45914 | L50: Completed | M50: 1. Already gather the information from IT Team 2. Already developed the activity Plan 3. Already support any documents for Gap Analysis 4. Already conducted the Internal Audit Agenda | N50: 1. Ensure the follow-up for CAR 2. Conduct the Management Review Agenda | O50: N/A | P50: =Project_Tracker[[#This Row],[End Date]]-Project_Tracker[[#This Row],[Target Date]] -> 0 | S50: =IF(Project_Tracker[[#This Row],[Project Lead]]="", "", IFERROR(VLOOKUP(Project_Tracker[[#This Row],[Project Lead]], Setting!C:D, 2, 0), "")) -> aldy_rienaldy@banpuindo.co.id | U50: =Project_Tracker[[#This Row],[Project Lead]]&", "&Project_Tracker[[#This Row],[Team Collaboration]] -> ALR, RRP | AC50: 2025
A51: 47 | B51: Management System | C51: Management System and Facilitation | D51: MS 8.2 | E51: Capability Development for Internal Auditor ISO 27001 | F51: ALR | G51: RRP | H51: 1 | I51: 45869 | J51: 45845 | K51: 45849 | L51: Completed | M51: 1. Already conduct discussion with HR Team regarding activities 2. Already conduct the 5 dyas of training including examination | O51: N/A | S51: =IF(Project_Tracker[[#This Row],[Project Lead]]="", "", IFERROR(VLOOKUP(Project_Tracker[[#This Row],[Project Lead]], Setting!C:D, 2, 0), "")) -> aldy_rienaldy@banpuindo.co.id | U51: =Project_Tracker[[#This Row],[Project Lead]]&", "&Project_Tracker[[#This Row],[Team Collaboration]] -> ALR, RRP | AC51: 2025
A52: 48 | B52: Management System | C52: Management System and Facilitation | D52: MS 9 | E52: Business Process Maturity Asessment | F52: ARS, ALR | G52: RRP, DHI | H52: 0 | I52: 45989 | L52: Open | S52: =IF(Project_Tracker[[#This Row],[Project Lead]]="", "", IFERROR(VLOOKUP(Project_Tracker[[#This Row],[Project Lead]], Setting!C:D, 2, 0), "")) | U52: =Project_Tracker[[#This Row],[Project Lead]]&", "&Project_Tracker[[#This Row],[Team Collaboration]] -> ARS, ALR, RRP, DHI | AC52: 2025
A53: 49 | B53: Management System | C53: Management System and Facilitation | D53: MS 10 | E53: Integrated ISO Certification Preparation and Readiness (ITM JKT) | F53: ALR | G53: RRP | H53: 0.3 | I53: 45989 | L53: Progress | M53: 1. Proposed initial Term of Requirements (TOR) 2. Conduct Initial Meeting with 3 Suppliers Candidates | N53: 1. Conduct Pre-Qualification with Supplier Candidates | S53: =IF(Project_Tracker[[#This Row],[Project Lead]]="", "", IFERROR(VLOOKUP(Project_Tracker[[#This Row],[Project Lead]], Setting!C:D, 2, 0), "")) -> aldy_rienaldy@banpuindo.co.id | U53: =Project_Tracker[[#This Row],[Project Lead]]&", "&Project_Tracker[[#This Row],[Team Collaboration]] -> ALR, RRP | AC53: 2025
A54: 50 | B54: Management System | C54: Management System and Facilitation | D54: MS 11 | E54: 2025 Consolidate and align the CS Strategic Planning and performance | F54: ASN | G54: ARS | H54: 0.9 | I54: Q1 | L54: Progress | S54: =IF(Project_Tracker[[#This Row],[Project Lead]]="", "", IFERROR(VLOOKUP(Project_Tracker[[#This Row],[Project Lead]], Setting!C:D, 2, 0), "")) -> andri_s@banpuindo.co.id | U54: =Project_Tracker[[#This Row],[Project Lead]]&", "&Project_Tracker[[#This Row],[Team Collaboration]] -> ASN, ARS | AC54: 2025
A55: 51 | B55: Management System | C55: Management System and Facilitation | D55: MS 12 | E55: Monitoring CS Performance Management Review and follow up action items. | F55: ASN | G55: ARS, DHI | H55: 0.1 | I55: H1-H2 | L55: Progress | S55: =IF(Project_Tracker[[#This Row],[Project Lead]]="", "", IFERROR(VLOOKUP(Project_Tracker[[#This Row],[Project Lead]], Setting!C:D, 2, 0), "")) -> andri_s@banpuindo.co.id | U55: =Project_Tracker[[#This Row],[Project Lead]]&", "&Project_Tracker[[#This Row],[Team Collaboration]] -> ASN, ARS, DHI | AC55: 2025
A56: 52 | B56: Management System | C56: Management System and Facilitation | D56: MS 13 | E56: ITM QAR System Implementation and Monitoring | F56: RRP | G56: ALR, DHI | H56: 0.8 | I56: H1-H2 | L56: Progress | M56: 1. Prepare guidance to follow up TIMES QAR Findings using QAR Apps & TIMES QAR ALPHA 2. Ensure readiness tools for follow up 3. Update guidance 4. Communication to assurer & assuree after TIMES QAR Procedure socialization on 21 July 2025 5. Send update progress and remind guidance how to follow up using Site Pre Closing Room (W3 SEP) 6. Send email wrap up progress update & action required to all sites | N56: Pendampingan kepada Assuree untuk pembuatan follow up action plan for new approach | S56: =IF(Project_Tracker[[#This Row],[Project Lead]]="", "", IFERROR(VLOOKUP(Project_Tracker[[#This Row],[Project Lead]], Setting!C:D, 2, 0), "")) -> ratih_putri@banpuindo.co.id | U56: =Project_Tracker[[#This Row],[Project Lead]]&", "&Project_Tracker[[#This Row],[Team Collaboration]] -> RRP, ALR, DHI | AC56: 2025
A57: 53 | B57: Management System | C57: Management System and Facilitation | D57: MS 14 | E57: 2025 TIMES QAR Implementation | F57: ALR | G57: ASN, RRP, DHI | H57: 0.7 | I57: 45930 | L57: Progress | M57: 1. Already present to Pak Wur and HSEC team for the initial TIMES QAR 2025 2. Already follow up concern from last meeting 3. Conduct discussion with internal MSBP for TIMES QAR 2025 implementation option 4. Conduct discussion with HSEC to decide the option 5. Conduct discussion with Pak Puji to get Direction 6. Approval Governance 7. Provide timeline of implementation | N57: 1. User Training Proposals 2. Lead and monitor the timeline - Meeting with Mine Head 3. Lead and monitor the timeline - Focusing on User Training | S57: =IF(Project_Tracker[[#This Row],[Project Lead]]="", "", IFERROR(VLOOKUP(Project_Tracker[[#This Row],[Project Lead]], Setting!C:D, 2, 0), "")) -> aldy_rienaldy@banpuindo.co.id | U57: =Project_Tracker[[#This Row],[Project Lead]]&", "&Project_Tracker[[#This Row],[Team Collaboration]] -> ALR, ASN, RRP, DHI | AC57: 2025
B58: Management System | C58: Management System and Facilitation | D58: MS 15 | E58: DOA Review and Revise executed as agreed plan (from IA recommendation regarding ICOMS-DOA) | F58: ALR | G58: DHI | H58: 1 | I58: 45838 | J58: 45872 | K58: 45960 | L58: Completed | M58: 1. Adjustment of value, period, and approver contract parameters in ICOMS refers to the new ITM DOA table 2. Addition of the Mining Business Indonesia (MBI) and Enabler attributes to the contract type 3. Deletion of ”banking” category on area of service in ICOMS 4. Agreeing on the reference matrix of contract types versus DOA provisions 5. Finalize the BA related ICOMS-DOA Enhancement | O58: N/A | S58: =IF(Project_Tracker[[#This Row],[Project Lead]]="", "", IFERROR(VLOOKUP(Project_Tracker[[#This Row],[Project Lead]], Setting!C:D, 2, 0), "")) -> aldy_rienaldy@banpuindo.co.id | U58: =Project_Tracker[[#This Row],[Project Lead]]&", "&Project_Tracker[[#This Row],[Team Collaboration]] -> ALR, DHI | AC58: 2025
A59: 54 | B59: Management System | C59: Management System and Facilitation | D59: MS 16 | E59: DOA Review and Revise executed as agreed plan e-CA-DOA) | F59: ALR | G59: DHI | H59: 0.2 | I59: 45985 | J59: 45954 | K59: 45985 | L59: Progress | M59: 1. Conduct Initial Meeting 2. Propose for Scenario Testing« 3. Conduct internal discussion among MSBP to analyze the SpeedIT regarding e-CA | N59: 1. Conduct testing 2. Follow-Up from the testing results 3. Review all final results 4. Release BA | O59: N/A | S59: =IF(Project_Tracker[[#This Row],[Project Lead]]="", "", IFERROR(VLOOKUP(Project_Tracker[[#This Row],[Project Lead]], Setting!C:D, 2, 0), "")) -> aldy_rienaldy@banpuindo.co.id | U59: =Project_Tracker[[#This Row],[Project Lead]]&", "&Project_Tracker[[#This Row],[Team Collaboration]] -> ALR, DHI | AC59: 2025
A60: 55 | B60: Management System | C60: Management System and Facilitation | D60: MS 16 | E60: DOA Communication (ITM DOA Survey) | F60: ALR | G60: RRP | H60: 1 | I60: 45838 | J60: 45719 | K60: 45838 | L60: Completed | M60: 1. Already planned for "MOTION - DOA Socialization'' 2. Already conduct socialization of DOA Communication to MELAK Group (TCM, BEK, TIS, NPR, GPK) 3. Publish "MOTION" to socialize the updated DOA Survey to all sites | O60: N/A | P60: =Project_Tracker[[#This Row],[End Date]]-Project_Tracker[[#This Row],[Target Date]] -> 0 | S60: =IF(Project_Tracker[[#This Row],[Project Lead]]="", "", IFERROR(VLOOKUP(Project_Tracker[[#This Row],[Project Lead]], Setting!C:D, 2, 0), "")) -> aldy_rienaldy@banpuindo.co.id | U60: =Project_Tracker[[#This Row],[Project Lead]]&", "&Project_Tracker[[#This Row],[Team Collaboration]] -> ALR, RRP | AC60: 2025
A61: 56 | B61: Management System | C61: Management System and Facilitation | D61: MS 17 | E61: MS and CI Sharing Knowledge Program (e.g. Benchmark) | F61: ALR, RSW | G61: RRP, BEY | H61: 0.05 | I61: 45930 | L61: Progress | S61: =IF(Project_Tracker[[#This Row],[Project Lead]]="", "", IFERROR(VLOOKUP(Project_Tracker[[#This Row],[Project Lead]], Setting!C:D, 2, 0), "")) | U61: =Project_Tracker[[#This Row],[Project Lead]]&", "&Project_Tracker[[#This Row],[Team Collaboration]] -> ALR, RSW, RRP, BEY | AC61: 2025
A62: 57 | B62: Management System | C62: Management System and Facilitation | D62: MS 18 | E62: 2025 MSBP/SPM/Quality/MS Integrated Plan Meeting | F62: ASN | G62: ALR, RSW | H62: 0 | I62: Q1 | L62: Open | S62: =IF(Project_Tracker[[#This Row],[Project Lead]]="", "", IFERROR(VLOOKUP(Project_Tracker[[#This Row],[Project Lead]], Setting!C:D, 2, 0), "")) -> andri_s@banpuindo.co.id | U62: =Project_Tracker[[#This Row],[Project Lead]]&", "&Project_Tracker[[#This Row],[Team Collaboration]] -> ASN, ALR, RSW | AC62: 2025
A63: 58 | B63: Management System | C63: Management System and Facilitation | D63: MS 19 | E63: Quality/SPM/MSBP Periodical Coordination Meeting | F63: ALR, RSW | G63: RRP, BEY | H63: 0 | I63: H1-H2 | L63: Open | S63: =IF(Project_Tracker[[#This Row],[Project Lead]]="", "", IFERROR(VLOOKUP(Project_Tracker[[#This Row],[Project Lead]], Setting!C:D, 2, 0), "")) | U63: =Project_Tracker[[#This Row],[Project Lead]]&", "&Project_Tracker[[#This Row],[Team Collaboration]] -> ALR, RSW, RRP, BEY | AC63: 2025
B64: Management System | C64: BP - Development & Procedure Alignment | D64: MS 20 | E64: ERSM (Strategy and Performance Management) | F64: ALR | H64: 1 | I64: 46022 | J64: 45306 | K64: 46022 | L64: Completed | M64: 1. Already designed for BP L1-3 - ERSM 2. Already develop Flow Process + RASCI 3. Already identified the required governance 4. Already draft for Governance related Strategy & Performance, Risk Management, and Compliance | N64: Monitor for approval | O64: N/A | P64: =Project_Tracker[[#This Row],[End Date]]-Project_Tracker[[#This Row],[Target Date]] -> 0 | S64: =IF(Project_Tracker[[#This Row],[Project Lead]]="", "", IFERROR(VLOOKUP(Project_Tracker[[#This Row],[Project Lead]], Setting!C:D, 2, 0), "")) -> aldy_rienaldy@banpuindo.co.id | U64: =Project_Tracker[[#This Row],[Project Lead]]&", "&Project_Tracker[[#This Row],[Team Collaboration]] -> ALR, | AC64: 2025
B65: Management System | C65: BP - Development & Procedure Alignment | E65: New Business Requirement Development | F65: DHI | L65: Open | S65: =IF(Project_Tracker[[#This Row],[Project Lead]]="", "", IFERROR(VLOOKUP(Project_Tracker[[#This Row],[Project Lead]], Setting!C:D, 2, 0), "")) -> dhany_indraswara@banpuindo.co.id | U65: =Project_Tracker[[#This Row],[Project Lead]]&", "&Project_Tracker[[#This Row],[Team Collaboration]] -> DHI, | AC65: 2025
B66: Management System | C66: BP - Development & Procedure Alignment | E66: Coal Supply Management Governance Development | F66: DHI | L66: Open | S66: =IF(Project_Tracker[[#This Row],[Project Lead]]="", "", IFERROR(VLOOKUP(Project_Tracker[[#This Row],[Project Lead]], Setting!C:D, 2, 0), "")) -> dhany_indraswara@banpuindo.co.id | U66: =Project_Tracker[[#This Row],[Project Lead]]&", "&Project_Tracker[[#This Row],[Team Collaboration]] -> DHI, | AC66: 2025
B67: Management System | C67: BP - Development & Procedure Alignment | E67: ERP Implementation | F67: DHI | L67: Open | S67: =IF(Project_Tracker[[#This Row],[Project Lead]]="", "", IFERROR(VLOOKUP(Project_Tracker[[#This Row],[Project Lead]], Setting!C:D, 2, 0), "")) -> dhany_indraswara@banpuindo.co.id | U67: =Project_Tracker[[#This Row],[Project Lead]]&", "&Project_Tracker[[#This Row],[Team Collaboration]] -> DHI, | AC67: 2025
B68: Management System | C68: BP - Development & Procedure Alignment | E68: EBP (3rd Party Coal) Process Allign With Application | F68: DHI | L68: Open | S68: =IF(Project_Tracker[[#This Row],[Project Lead]]="", "", IFERROR(VLOOKUP(Project_Tracker[[#This Row],[Project Lead]], Setting!C:D, 2, 0), "")) -> dhany_indraswara@banpuindo.co.id | U68: =Project_Tracker[[#This Row],[Project Lead]]&", "&Project_Tracker[[#This Row],[Team Collaboration]] -> DHI, | AC68: 2025
B69: Management System | C69: BP - Development & Org Alignment | E69: IBP (Including CPI) | F69: DHI | L69: Open | S69: =IF(Project_Tracker[[#This Row],[Project Lead]]="", "", IFERROR(VLOOKUP(Project_Tracker[[#This Row],[Project Lead]], Setting!C:D, 2, 0), "")) -> dhany_indraswara@banpuindo.co.id | U69: =Project_Tracker[[#This Row],[Project Lead]]&", "&Project_Tracker[[#This Row],[Team Collaboration]] -> DHI, | AC69: 2025
B70: Management System | C70: BP - Development & Procedure Alignment | D70: MS 21 | E70: Forestry & Enviro Management | F70: ARS | G70: DHY | H70: 0.85 | I70: 46021 | L70: Progress | M70: Review & finalize Management Standard Rehab DAS with FEM team | N70: Look forward for final review from Pak Andri and getting approval | O70: Tight schedule from PO | S70: =IF(Project_Tracker[[#This Row],[Project Lead]]="", "", IFERROR(VLOOKUP(Project_Tracker[[#This Row],[Project Lead]], Setting!C:D, 2, 0), "")) -> aditya_r@banpuindo.co.id | U70: =Project_Tracker[[#This Row],[Project Lead]]&", "&Project_Tracker[[#This Row],[Team Collaboration]] -> ARS, DHY | AC70: 2025
B71: Management System | C71: BP - Development & Procedure Alignment | D71: MS 22 | E71: F M C | F71: ARS | H71: 0.85 | I71: 46022 | L71: Progress | M71: Already develop SOP Innovation value capture, financial data steward (financial dashboard) and budget execution | N71: Review session with FMC Head for SOP finalizatiom | O71: Tight schedule from PO | S71: =IF(Project_Tracker[[#This Row],[Project Lead]]="", "", IFERROR(VLOOKUP(Project_Tracker[[#This Row],[Project Lead]], Setting!C:D, 2, 0), "")) -> aditya_r@banpuindo.co.id | U71: =Project_Tracker[[#This Row],[Project Lead]]&", "&Project_Tracker[[#This Row],[Team Collaboration]] -> ARS, | AC71: 2025
B72: Management System | C72: BP - Development & Procedure Alignment | D72: MS 23 | E72: ERSM (Compliance and Risk) | F72: ALR | H72: 1 | I72: 46022 | J72: 45306 | K72: 46022 | L72: Completed | M72: 1. Already designed for BP L1-3 - ERSM 2. Already develop Flow Process + RASCI 3. Already identified the required governance 4. Already draft for Policy and SOP related Strategy & Performance, Risk Management, and Compliance 5. Already finalized the Policy and Management Standard for Risk Management and Compliance | N72: 1. Continue monitoring PO for approval documents | O72: N/A | P72: =Project_Tracker[[#This Row],[End Date]]-Project_Tracker[[#This Row],[Target Date]] -> 0 | AC72: 2025
B73: Management System | C73: BP - Development & Procedure Alignment | D73: MS 24 | E73: HALO Digital Project | F73: ARS | G73: RRP | H73: 0 | L73: Open | S73: =IF(Project_Tracker[[#This Row],[Project Lead]]="", "", IFERROR(VLOOKUP(Project_Tracker[[#This Row],[Project Lead]], Setting!C:D, 2, 0), "")) -> aditya_r@banpuindo.co.id | U73: =Project_Tracker[[#This Row],[Project Lead]]&", "&Project_Tracker[[#This Row],[Team Collaboration]] -> ARS, RRP | AC73: 2025
B74: Management System | C74: BP - Development & Org Alignment | D74: MS 25 | E74: ITM Transformation Office | F74: ASN | G74: ARS, DHI | H74: 0.5 | I74: 45835 | J74: 45813 | L74: Open | S74: =IF(Project_Tracker[[#This Row],[Project Lead]]="", "", IFERROR(VLOOKUP(Project_Tracker[[#This Row],[Project Lead]], Setting!C:D, 2, 0), "")) -> andri_s@banpuindo.co.id | U74: =Project_Tracker[[#This Row],[Project Lead]]&", "&Project_Tracker[[#This Row],[Team Collaboration]] -> ASN, ARS, DHI | AC74: 2025
B75: Management System | C75: BP - Development & Org Alignment | D75: MS 31 | E75: Digital and Innovation | F75: ASN | H75: 1 | L75: Open | S75: =IF(Project_Tracker[[#This Row],[Project Lead]]="", "", IFERROR(VLOOKUP(Project_Tracker[[#This Row],[Project Lead]], Setting!C:D, 2, 0), "")) -> andri_s@banpuindo.co.id | U75: =Project_Tracker[[#This Row],[Project Lead]]&", "&Project_Tracker[[#This Row],[Team Collaboration]] -> ASN, | AC75: 2025
B76: Management System | C76: BP - Development & Procedure Alignment | D76: MS 26 | E76: Issue Management and Resettlement Management | F76: ALR | H76: 0.1 | K76: 45960 | L76: Progress | S76: =IF(Project_Tracker[[#This Row],[Project Lead]]="", "", IFERROR(VLOOKUP(Project_Tracker[[#This Row],[Project Lead]], Setting!C:D, 2, 0), "")) -> aldy_rienaldy@banpuindo.co.id | U76: =Project_Tracker[[#This Row],[Project Lead]]&", "&Project_Tracker[[#This Row],[Team Collaboration]] -> ALR, | AC76: 2025
B77: Management System | C77: BP - Development & Org Alignment | D77: MS 27 | E77: Mineral Project Phase 1 | F77: ALR | G77: ARS | H77: 1 | I77: 45869 | J77: 45831 | K77: 45855 | L77: Completed | M77: 1. Coordinate with stakeholders to get the aspiration, strategy, and objectives 2. Coordinate with stakeholders in fulfillment of Mineral Project Phase 1 BPM Worksheet 3. Develop Business Process High Level (Explaining each wave) 4. Conduct iteration meeting to finetune the BP Design 5. Present to Director for approval | N77: 1. Conduct Approval on BP Design (Waiting HRMC Results) | O77: N/A | S77: =IF(Project_Tracker[[#This Row],[Project Lead]]="", "", IFERROR(VLOOKUP(Project_Tracker[[#This Row],[Project Lead]], Setting!C:D, 2, 0), "")) -> aldy_rienaldy@banpuindo.co.id | U77: =Project_Tracker[[#This Row],[Project Lead]]&", "&Project_Tracker[[#This Row],[Team Collaboration]] -> ALR, ARS | AC77: 2025
B78: Management System | C78: BP - Development & Procedure Alignment | D78: MS 28 | E78: Internal Audit Enhancement | F78: ALR | G78: DHI | H78: 1 | I78: 45937 | J78: 45855 | K78: 45937 | L78: Completed | M78: 1. Already produced draft – IA Manual 2. Already draft - IA Business Process L2-3 (New) 3. Already draft - IA Business Process L4 4. Already draft - 3 SOP of IA 5. Confirm the IA BP & SOP 6. Finalize all Documents | N78: 1. Monitor the Approval | O78: N/A | S78: =IF(Project_Tracker[[#This Row],[Project Lead]]="", "", IFERROR(VLOOKUP(Project_Tracker[[#This Row],[Project Lead]], Setting!C:D, 2, 0), "")) -> aldy_rienaldy@banpuindo.co.id | U78: =Project_Tracker[[#This Row],[Project Lead]]&", "&Project_Tracker[[#This Row],[Team Collaboration]] -> ALR, DHI | AC78: 2025
B79: Management System | C79: BP - Development & Procedure Alignment | D79: MS.30 | E79: ROM & FC Safety Stock Implementation | F79: ARS | H79: 0.9 | I79: 46016 | J79: 45869 | K79: 46016 | L79: Progress | M79: SOP ROM & FC Safety Stock already developed and did role play with stackholders | N79: Update for SOP ROM & FC Safety Stock refer to role play | S79: =IF(Project_Tracker[[#This Row],[Project Lead]]="", "", IFERROR(VLOOKUP(Project_Tracker[[#This Row],[Project Lead]], Setting!C:D, 2, 0), "")) -> aditya_r@banpuindo.co.id | U79: =Project_Tracker[[#This Row],[Project Lead]]&", "&Project_Tracker[[#This Row],[Team Collaboration]] -> ARS, | AC79: 2025
B80: Management System | C80: BP - Development & Procedure Alignment | D80: MS.31 | E80: Shipment Document Vessel (Tax & SC) | F80: ARS | H80: 1 | I80: 45930 | L80: Completed | M80: Flow Process for Shipment Document Vessel already developed | N80: SOP Establishment with SC Team | S80: =IF(Project_Tracker[[#This Row],[Project Lead]]="", "", IFERROR(VLOOKUP(Project_Tracker[[#This Row],[Project Lead]], Setting!C:D, 2, 0), "")) -> aditya_r@banpuindo.co.id | U80: =Project_Tracker[[#This Row],[Project Lead]]&", "&Project_Tracker[[#This Row],[Team Collaboration]] -> ARS, | AC80: 2025
B81: Management System | C81: BP - Development & Procedure Alignment | D81: MS.32 | E81: HR SOP Development | F81: ARS | H81: 0.75 | I81: 45930 | L81: Progress | M81: -SOP Industrial Relation Dispute and Managing Employee Complaint done '-SOP Payroll, Employee Loan and SOP Employee Personal Data done | N81: Getting approval for SOP | S81: =IF(Project_Tracker[[#This Row],[Project Lead]]="", "", IFERROR(VLOOKUP(Project_Tracker[[#This Row],[Project Lead]], Setting!C:D, 2, 0), "")) -> aditya_r@banpuindo.co.id | U81: =Project_Tracker[[#This Row],[Project Lead]]&", "&Project_Tracker[[#This Row],[Team Collaboration]] -> ARS, | AC81: 2025
B82: Management System & Business Process | D82: MS.33 | E82: Digital and Innovation | F82: DHI | L82: Open | S82: =IF(Project_Tracker[[#This Row],[Project Lead]]="", "", IFERROR(VLOOKUP(Project_Tracker[[#This Row],[Project Lead]], Setting!C:D, 2, 0), "")) -> dhany_indraswara@banpuindo.co.id | U82: =Project_Tracker[[#This Row],[Project Lead]]&", "&Project_Tracker[[#This Row],[Team Collaboration]] -> DHI, | AC82: 2025
B83: Management System | C83: BP - Development & Procedure Alignment | D83: MS.34 | E83: Shipment Coordination Procedures (Non BLMS) | F83: ARS | H83: 0.5 | I83: 46021 | L83: Progress | M83: Develop SOP for Shipment Doc : 1. Shipment Doc for vessel 2. Shipment Doc for direct barge 3. Shipment Doc for transhipment | N83: Waiting schedule for discuss and review with SC Team (tight schedule) | S83: =IF(Project_Tracker[[#This Row],[Project Lead]]="", "", IFERROR(VLOOKUP(Project_Tracker[[#This Row],[Project Lead]], Setting!C:D, 2, 0), "")) -> aditya_r@banpuindo.co.id | U83: =Project_Tracker[[#This Row],[Project Lead]]&", "&Project_Tracker[[#This Row],[Team Collaboration]] -> ARS, | AC83: 2025
B84: Management System | C84: BP - Development & Procedure Alignment | D84: MS.35 | E84: Contractor MAnagement and Engineering Enhancement | F84: ARS | H84: 0.75 | I84: 46021 | K84: 46021 | L84: Progress | M84: Develop SOP for 1. Contractor Engagement 2. Contractor Monitroing and Evaluation, 3. Contractor Work Completion 4. Contractor Performance Improvement | N84: Final review with stakeholders | S84: =IF(Project_Tracker[[#This Row],[Project Lead]]="", "", IFERROR(VLOOKUP(Project_Tracker[[#This Row],[Project Lead]], Setting!C:D, 2, 0), "")) -> aditya_r@banpuindo.co.id | U84: =Project_Tracker[[#This Row],[Project Lead]]&", "&Project_Tracker[[#This Row],[Team Collaboration]] -> ARS, | AC84: 2025
B85: Management System | C85: BP - Development & Procedure Alignment | D85: MS.36 | E85: Information Technology Governance | F85: ARS | H85: 1 | L85: Completed | M85: Finalized for SP for Application Architecture and Infrastructure, SP Aplication Workflow Engine and Guideline ITM Plaza reponsive for end user | N85: All procedures done | S85: =IF(Project_Tracker[[#This Row],[Project Lead]]="", "", IFERROR(VLOOKUP(Project_Tracker[[#This Row],[Project Lead]], Setting!C:D, 2, 0), "")) -> aditya_r@banpuindo.co.id | U85: =Project_Tracker[[#This Row],[Project Lead]]&", "&Project_Tracker[[#This Row],[Team Collaboration]] -> ARS, | AC85: 2025
A86: 59 | B86: Continuous Improvement | C86: Innovation Program and Implementation | D86: CI 1.1 | E86: ITM Innovation Strategic Deployment | F86: ASN | G86: RSW, AFZ, BEY | H86: 0.3 | I86: Q1 | L86: Progress | S86: =IF(Project_Tracker[[#This Row],[Project Lead]]="", "", IFERROR(VLOOKUP(Project_Tracker[[#This Row],[Project Lead]], Setting!C:D, 2, 0), "")) -> andri_s@banpuindo.co.id | U86: =Project_Tracker[[#This Row],[Project Lead]]&", "&Project_Tracker[[#This Row],[Team Collaboration]] -> ASN, RSW, AFZ, BEY | AC86: 2025
A87: 60 | B87: Continuous Improvement | C87: Innovation Program and Implementation | D87: CI 1.2 | E87: Establisment of Innovation Strategic Deployment (e.g. Institutionalized at Site Level for managing Innovation) | F87: RSW | G87: AFZ, BEY | H87: 0.2 | I87: H1 | L87: Progress | M87: 1. Developed the scheme & timeline 2. Conducted first filtering the ITM SI 2025 3. Already discuss & review the scheme with ERSM Dept.(20 May '25) 4. Already discussed with DCC Head (21 May '25) | N87: 1. Coordination with ITM Innovation Working Committee | S87: =IF(Project_Tracker[[#This Row],[Project Lead]]="", "", IFERROR(VLOOKUP(Project_Tracker[[#This Row],[Project Lead]], Setting!C:D, 2, 0), "")) -> reza_suryawardhana@banpuindo.co.id | U87: =Project_Tracker[[#This Row],[Project Lead]]&", "&Project_Tracker[[#This Row],[Team Collaboration]] -> RSW, AFZ, BEY | AC87: 2025
A88: 6 | B88: Management System | C88: ITM Integrated Management System (TIMES) Element/Standard Deployment | D88: MS 2.3 | E88: Innovation Management | F88: BEY | G88: RSW, AFZ | H88: 0.9 | I88: Q2-H1 | L88: Progress | M88: Reviewed: 1. Innovation Strategic Deployment 2. Idea Generation & Prioritization 3. Stage Gate Process 4. Idea Blast 5. Strategic Project Tracking and Monitoring 6. Operational Project Tracking and Monitoring | N88: Next review: 1. ITMNovation Convention 2. Site Innovation Convention JKT-IBO 3. Innovation Communication 4. Innovation QMS & System Development | O88: D&I Plan Impacted to Innovation BP draft. | R88: CI Governance Tracking Worksheet | S88: =IF(Project_Tracker[[#This Row],[Project Lead]]="", "", IFERROR(VLOOKUP(Project_Tracker[[#This Row],[Project Lead]], Setting!C:D, 2, 0), "")) -> bella_yolanda@banpuindo.co.id | U88: =Project_Tracker[[#This Row],[Project Lead]]&", "&Project_Tracker[[#This Row],[Team Collaboration]] -> BEY, RSW, AFZ | AC88: 2025
A89: 61 | B89: Continuous Improvement | C89: Innovation Program and Implementation | D89: CI 1.3 | E89: Benchmarking Program | F89: BEY | G89: AFZ | H89: 0.9 | I89: H1 | L89: Hold | M89: 1. Send TOR to PAMA (18/02) 2. Initial Coordination with PAMA (10/03) 3. Agreed to conduct Benchmark on May 13th, 2025 4. Send email to Function Heads to assign representative from each Dept - HR, DCOE (11/04) 5. Request CA for Transport & Meals fees 6. Create preparation group Teams chat & invitation to Site SPM/ DSPM (24/04) 7. Request souvenir to CC (24/04) | N89: Postponed due to PAMA readiness | S89: =IF(Project_Tracker[[#This Row],[Project Lead]]="", "", IFERROR(VLOOKUP(Project_Tracker[[#This Row],[Project Lead]], Setting!C:D, 2, 0), "")) -> bella_yolanda@banpuindo.co.id | U89: =Project_Tracker[[#This Row],[Project Lead]]&", "&Project_Tracker[[#This Row],[Team Collaboration]] -> BEY, AFZ | AC89: 2025
A90: 63 | B90: Continuous Improvement | C90: Innovation Program and Implementation | D90: CI 1.5 | E90: Innovation Portfolio Management | F90: RSW | G90: BEY | H90: 0.18 | I90: H1 | L90: Progress | M90: 1. Concept already developed | S90: =IF(Project_Tracker[[#This Row],[Project Lead]]="", "", IFERROR(VLOOKUP(Project_Tracker[[#This Row],[Project Lead]], Setting!C:D, 2, 0), "")) -> reza_suryawardhana@banpuindo.co.id | U90: =Project_Tracker[[#This Row],[Project Lead]]&", "&Project_Tracker[[#This Row],[Team Collaboration]] -> RSW, BEY | AC90: 2025
A91: 64 | B91: Continuous Improvement | C91: Innovation Program and Implementation | D91: CI 1.6 | E91: Innovation Maturity Assessment & Enhancement Program | F91: RSW | G91: AFZ, BEY | H91: 0.9 | I91: H1 | L91: Progress | M91: 1. Reviewed proposal from CIAS 2. Developed vendor comparison between CIAS, APQC, Outcome 3. Discussed & receipt proposal from PPM 4. Conduct discussion with PPM Manajemen to explain their proposal (30 May '25) 5. Update Vendor comparison (add PPM Manajemen) 6. Already discussed with MSBP Head & CI Member relate with vendor comparison 7. Already communication with Banpu Academy, currently they not yet have plan to conduct this matter but they're interested, so that they request to share the result later (17 Jun '25) 8. Agreed to elaborate more regarding Self-assessment by Gartner & APQC (17 Jun '25) 9. Select 2 best vendor 10. Analyze of feasibility, approach & other paramaters 11. Selected the proper approcah (Gartner) 12. Analyze the Gartner assessment items that relevan with target participants 13. Agreed to select relevan tartget participant (CI-MSBP, DPSM, SPM, DCC & OM) 14. Conducted explanation session to DSPM Melak (6 Oct '25, DSPM IMM & OM TRUST (9 Oct '25) 15. Already 100% participant fill in assessment form 16 Develop data compilation per site & get the score 17. Develop data aggregate to ITM Group level and get the score 18. For ITM Group Level Innovation Maturity Self Assessment Score is 3.28 | N91: 1. Seek schedule to conduct FGD with all related participants 2. Set action plan based on result from FGD Session | S91: =IF(Project_Tracker[[#This Row],[Project Lead]]="", "", IFERROR(VLOOKUP(Project_Tracker[[#This Row],[Project Lead]], Setting!C:D, 2, 0), "")) -> reza_suryawardhana@banpuindo.co.id | U91: =Project_Tracker[[#This Row],[Project Lead]]&", "&Project_Tracker[[#This Row],[Team Collaboration]] -> RSW, AFZ, BEY | AC91: 2025
A92: 65 | B92: Continuous Improvement | C92: Innovation Program and Implementation | D92: CI 1.7 | E92: Innovation Ecosystem (Initiated) | F92: AFZ | G92: BEY, RSW | H92: 0.5 | I92: H1-H2 | J92: 45663 | K92: 46010 | L92: Progress | M92: - Created draft big action plan program Innovation Ecosystem - Drafted innovation eco-system program [in detail] '- Schedule time for discussion first draft - Agreed draft proposal [Conduct discussion] | N92: - Finalize the proposal | S92: =IF(Project_Tracker[[#This Row],[Project Lead]]="", "", IFERROR(VLOOKUP(Project_Tracker[[#This Row],[Project Lead]], Setting!C:D, 2, 0), "")) -> afrizon_afrizon@banpuindo.co.id | U92: =Project_Tracker[[#This Row],[Project Lead]]&", "&Project_Tracker[[#This Row],[Team Collaboration]] -> AFZ, BEY, RSW | AC92: 2025
A93: 62 | B93: Continuous Improvement | C93: Innovation Program and Implementation | D93: CI 1.4 | E93: Strengthen Innovative Culture (e.g., Bootcamp/Innovation Hack, Innovation Show) | F93: BEY | G93: RSW, AFZ | H93: 1 | I93: H1-H2 | L93: Completed | M93: 1. CI internal meeting & coordinate with HR - agenda proposal (11/06) 2. Review by MSBP Head (16/06) 3. Discuss with DCC (19/06) 4. Learning Design Deck & Innovation Agenda (24/06) BHSS (Done - July) 1. Define concept (02/07) 2. Key speaker selection (10/07) 3. TOR development & review (17/07) 4. Master design from CC (22/07) 5. Moderator brief (24/07) 6. Key Speaker technical meeting (25/07) Innovation Promotion through QCD (Done - August) 1. Request from CC (04/08) 2. Create communication group with Project team (05/08) 3. Brief to Project team (08/08) Innovation Talkshow in collab with HSEC & DCC (Cancelled): 1. Initial email to HSEC (20/08) 2. Initial meeting with HSEC & DCC (03/09) 3. TOR sent to HSEC (08/09) Innovation Talkshow in collab with HR (Done - October) 1. Scheme re-discussion (12/09) 2. TOR development (16/09) 3. Seeking Speaker (Done - Tyo Guritno) 4. Alignment with Tyo Guritno (Done) 5. Meals preparation (Done) | O93: Budget | S93: =IF(Project_Tracker[[#This Row],[Project Lead]]="", "", IFERROR(VLOOKUP(Project_Tracker[[#This Row],[Project Lead]], Setting!C:D, 2, 0), "")) -> bella_yolanda@banpuindo.co.id | U93: =Project_Tracker[[#This Row],[Project Lead]]&", "&Project_Tracker[[#This Row],[Team Collaboration]] -> BEY, RSW, AFZ | AC93: 2025
A94: 67 | B94: Continuous Improvement | D94: CI 3 | E94: Innovation PMO/Facilitating/Coaching/Clinic Program for each Initiatives | F94: RSW | G94: BEY, AFZ | H94: 1 | I94: H1-H2 | J94: 45669 | K94: 46011 | L94: Completed | M94: 1. Facilitated DT & Preparation Kick Off Project Times Cepat 2. Facilitated ADAPtTIC Project 3. Faciliated TREIN #2 4. Facilitated PLIS Phase #2 Adoption 5. Facilitate Vehicnle Management System 6. Facilitate GA improvement project 7. Support to facilitate Procurement & IT RPA Project 8. Facilitated CC Project Initiatives 9. ADAPTIC : Prepare to Go Live 10. TREIN #2 revisit score, sprint plan & team member 11. TRIMS in analyze &ensure there's no double benefit to employee, relate with traveling to join event & workshop 12. PLIS adoption : follow up to set socialization & training for NPR Employee 13. Vehicnle Management System : progress AI Vision POC already 75% & waiting update from Autogate paroject progress & timeline 14. GA Accomodation Improvement : Finalization Project Charter & prepare to submit registration to INOC 14. RPA Project : Prepare G1 Submission 15. All related proejct already join JKT Innovation Convention | S94: =IF(Project_Tracker[[#This Row],[Project Lead]]="", "", IFERROR(VLOOKUP(Project_Tracker[[#This Row],[Project Lead]], Setting!C:D, 2, 0), "")) -> reza_suryawardhana@banpuindo.co.id | U94: =Project_Tracker[[#This Row],[Project Lead]]&", "&Project_Tracker[[#This Row],[Team Collaboration]] -> RSW, BEY, AFZ | AC94: 2025
A95: 68 | B95: Continuous Improvement | D95: CI 4 | E95: Innovation Center (INOC) Roll Out and Monitoring | F95: AFZ | G95: RSW, BEY | H95: 1 | I95: H1-H2 | J95: 45663 | K95: 45835 | L95: Completed | M95: - Listed issue from TCM-BEK - Follow up to Tim IT for the issue - Follw up issue INOC TCM BEK - Discussion for plan INOC V.04 - Trial data INOC submission for AI [Preparation] - Identify issue user BKK can't login INOC - Follow up issue Melak Cluster for user not linkage with HRIS - Socialization INOC to Team Project ITM Gaja Mada - Follow up flow approval Idea Blast - Solvig Issue TRUST & Melak by Accident - Draft matrial socialization for Gajah Mada Project - 'Create requirement INOC 4.0 - Discuss with P' Achmy & Team Dev for issue from Melak & TRUST (Can't update Automatically from database for new role direct superior) - Draft for new requirement Dashboards INOC Innitiatives related with ITM Business Process | N95: - Continued conduct biweekly update AI requirement development - Collect data requirement from each site | O95: - Need some adjustment for user/role | S95: =IF(Project_Tracker[[#This Row],[Project Lead]]="", "", IFERROR(VLOOKUP(Project_Tracker[[#This Row],[Project Lead]], Setting!C:D, 2, 0), "")) -> afrizon_afrizon@banpuindo.co.id | U95: =Project_Tracker[[#This Row],[Project Lead]]&", "&Project_Tracker[[#This Row],[Team Collaboration]] -> AFZ, RSW, BEY | AC95: 2025
A96: 70 | B96: Continuous Improvement | D96: CI 6 | E96: Innovation Adoption and Impact Monitoring for each initiatives/Value Tracking | F96: AFZ | G96: BEY, RSW | H96: 0.75 | I96: H1-H2 | J96: 45677 | K96: 45744 | L96: Progress | M96: - List up Project Completed to follow regulation Adoption and Impact Tracking - Confirm to PO for participate Adoption and impact tracking - Drafting scheme for monitorig - Draft data submission for dashboard monitoring to PBI - Drafting governance Project Adoption [MS/SOP] | N96: - Continue discuss for finalize Governance (MS & SP) Project Adoption & Benefit Impact Tracking | O96: - status project due date of end off moitoring | S96: =IF(Project_Tracker[[#This Row],[Project Lead]]="", "", IFERROR(VLOOKUP(Project_Tracker[[#This Row],[Project Lead]], Setting!C:D, 2, 0), "")) -> afrizon_afrizon@banpuindo.co.id | U96: =Project_Tracker[[#This Row],[Project Lead]]&", "&Project_Tracker[[#This Row],[Team Collaboration]] -> AFZ, BEY, RSW | AC96: 2025
A97: 71 | B97: Continuous Improvement | D97: CI 7 | E97: 2024 Success Project Expansion (SPEx) Implementation | F97: RSW | G97: BEY, AFZ | H97: 0.8 | I97: H1-H2 | J97: 45760 | K97: 46010 | L97: Progress | M97: 1. In progress to collect potential project initiative as candidates of 2025 SPEx Program 2. PLIS Phase #2 as SPEx Project 2025 3. Facilitating to conduct regular coordination with CRM Melak Team (conducted weekly coordination meeting every Wednesday 09.00 am WIB) 4. Conducted sharing & coordination with KTT NPR (2 Jul ’25) 5. Conducted socialization to NPR PIC Related as assigned by KTT NPR (17 Jul ’25) 6. Conduct sharing & coordination with KTT BEK (20 Aug ’25) 7. Get formal assignment of BEK PIC related from KTT BEK (9 Oct ’25) 8. Conducted socialization to BEK PIC related (27 – 28 Nov ’25) | N97: 1. Official rollout in BEK, TCM & GPK | S97: =IF(Project_Tracker[[#This Row],[Project Lead]]="", "", IFERROR(VLOOKUP(Project_Tracker[[#This Row],[Project Lead]], Setting!C:D, 2, 0), "")) -> reza_suryawardhana@banpuindo.co.id | U97: =Project_Tracker[[#This Row],[Project Lead]]&", "&Project_Tracker[[#This Row],[Team Collaboration]] -> RSW, BEY, AFZ | AC97: 2025
A98: 72 | B98: Continuous Improvement | D98: CI 8 | E98: 5S Program Implementation (e.g. 5S Hack, 5SxK3, ITM Clean Up Day, Training 5S, Audit 5S_Scoring_CAR) | F98: AFZ | G98: BEY | H98: 0.8 | I98: H1-H2 | J98: 45663 | K98: 46021 | L98: Progress | M98: - Drafted Proposal event 5SxK3 - Agreed Proposal 5SxK3 [Content Program & Budget - Discussed with K3 committee for alignment schedule and support - Drafted T&C for program "Lomba Kreatifitas" - Create CA as budget approved - Finalize T&C with Internal CI - Drafted content promotion "Lomba Kreatifitas" with K3 Committee - Update Kontrak RDPL on IPROC - Release Teaser "Lomba Kreativitas" - Follow up status Iproc - Created/submited contract RDPL to ICOMS - [Done] Follow up "blast teaser" Lomba Kreativitas Teaser #2 - [Done] Follow up Approval Contract RDPL on IProc - Preparation "Talkshop 5SxErgonomic" - Summary winner Lomba Poster 5SxK3 - Create Announcement for closing Month of K3 - Follow up Approval Proposal Vendor - ITM Strategic Objective discussion with Vendor - Create Timeliine for execute 5S Strategic alig with ITM Strategic Objectives | N98: - Drafting governance 5S Enhancement [MS] - Conduct training 5S with coordination HR | S98: =IF(Project_Tracker[[#This Row],[Project Lead]]="", "", IFERROR(VLOOKUP(Project_Tracker[[#This Row],[Project Lead]], Setting!C:D, 2, 0), "")) -> afrizon_afrizon@banpuindo.co.id | U98: =Project_Tracker[[#This Row],[Project Lead]]&", "&Project_Tracker[[#This Row],[Team Collaboration]] -> AFZ, BEY | AC98: 2025
A99: 66 | B99: Continuous Improvement | D99: CI 2 | E99: Innovation Learning Program Implementation 2.1. Innovation Learning Modules 2.2. Pre & Post Learning Management 2.3. In-House Expertise Development (e.g. TFT Mechanism) | F99: BEY | G99: RSW | H99: 0.9 | I99: H1-H2 | L99: Progress | M99: 1. Initial meeting with HR to get same understanding, discuss direction and aspiration from steerco & HR Head (14/01) 2. FU meeting with working team to develop proposal. 2025 modules agreed by all parties & plan to have SPM/ DSPM certified (30/01) 3. Arrange meeting with HRSS for CapDev (20/02) 4. Joined Learning Design Training (25-27/02) 5. Arrange internal meeting for Leading Change plan (10/03) 6. Presentation Skill to Project Team for 2025 BGIA (14/03) 7. Joined TTT Training (18-20/03) 8. Meeting with HR for New Onboarding Module (24/03) 9. Meeting with HR for technical module creation (25/03) 10. In-module Quiz (28/04) 11. Pre&Post Test (28/04) Update in email: Subject - 2025 Innovation Learning Update 1. Innovation Assessor (Innovation Judges Training) = Drop 2. Leading Change = Shifted to 2026 3. Business & Financial Analysis = Shifted to 2026 4. SM/ PO Certification = Shifted to 2026 5. Presentation Skill = Additional | N99: Innovation Mandatory Training to Existing Employee: 1. Training (27-28/ 10) Presentation Skill: 1. Consult with HR & Mas Agung (23 /10) | O99: Subscription for https://elevenlabs.io/app/home | S99: =IF(Project_Tracker[[#This Row],[Project Lead]]="", "", IFERROR(VLOOKUP(Project_Tracker[[#This Row],[Project Lead]], Setting!C:D, 2, 0), "")) -> bella_yolanda@banpuindo.co.id | U99: =Project_Tracker[[#This Row],[Project Lead]]&", "&Project_Tracker[[#This Row],[Team Collaboration]] -> BEY, RSW | AC99: 2025
A100: 69 | B100: Continuous Improvement | D100: CI 5 | E100: Innovation Promotion and Communication Program | F100: BEY | G100: RSW, AFZ | H100: 0.9 | I100: H1-H2 | L100: Progress | M100: 1. Release INSITION survey as riset (15/01) 2. Result compilation & action plan proposal (31/01) 3. Present survey result to internal (10/02) 4. Draft Project profile for 2025 BGIA (24/04) 5. Blast - Send-off for BGIA 2025 (05/05) 6. Blast - D-1 for BGIA 2025 (07/05) 7. Blast Band Reward 2025 BGIA (16/05) 8. Blast IB & INFINITY Promotion (09/06) 9. Initial discussion with CC (23/06) 10. First KV draft by CC (18/07) 11. 2nd KV draft by CC (22/07) 12. Meeting with ADAPt for communication requirement (25/07) 13. First draft of ADAPTIC communication (15/08) 14. 2nd draft of ADAPTIC communication (18/08) 15. 3rd draft of ADAPTIC communication (22/08) 16. Release of ADAPTIC communication (26/08) 17. ITMNovation teaser1 (25/09) 18. ITMNovation teaser 2 (29/09) 19. ITMNovation what's new (01/10) 20. JKT-IBO teaser (07/10) 21. JKT-IBO teaser resend (10/10) 22. Innovation Talkshow 1 (15/10) 23. Innovation Talkshow 2 (21/10) 24. Innovation Talkshow 3 (22/10) | S100: =IF(Project_Tracker[[#This Row],[Project Lead]]="", "", IFERROR(VLOOKUP(Project_Tracker[[#This Row],[Project Lead]], Setting!C:D, 2, 0), "")) -> bella_yolanda@banpuindo.co.id | U100: =Project_Tracker[[#This Row],[Project Lead]]&", "&Project_Tracker[[#This Row],[Team Collaboration]] -> BEY, RSW, AFZ | AC100: 2025
...

Sheet Setting
A1: Status | C1: Name | D1: Email
A2: Open | C2: RRP | D2: ratih_putri@banpuindo.co.id
A3: Completed | C3: DHI | D3: dhany_indraswara@banpuindo.co.id
A4: Hold | C4: BEY | D4: bella_yolanda@banpuindo.co.id
A5: Progress | C5: ASN | D5: andri_s@banpuindo.co.id
C6: RSW | D6: reza_suryawardhana@banpuindo.co.id
C7: ALR | D7: aldy_rienaldy@banpuindo.co.id
C8: ARS | D8: aditya_r@banpuindo.co.id
C9: AFZ | D9: afrizon_afrizon@banpuindo.co.id
